Decorators/__init__.py
Decorators/decorators.py
Decorators/main.py
guest881_Decorators-0.2.5.dist-info/METADATA
guest881_Decorators-0.2.5.dist-info/WHEEL
guest881_Decorators-0.2.5.dist-info/top_level.txt
guest881_Decorators-0.2.5.dist-info/RECORD
