Metadata-Version: 2.1
Name: guest881-Decorators
Version: 0.2.5
Summary: Decorators for gust881 programs，自嗨，自用，不定时增加优化，已优化几个小问题，新增异步尝试装饰器
Author: guest881
Author-email: axijwqmxqoxmqldnq@mzjgx.dpdns.org
License: MIT
Classifier: Programming Language :: Python :: 3
Classifier: License :: OSI Approved :: MIT License
Classifier: Operating System :: OS Independent
Requires-Python: >=3.8
Requires-Dist: loguru
